{
    "homepage": "https://github.com/qjfoidnh/BaiduPCS-Go",
    "version": "4.0.1",
    "license": "Apache-2.0",
    "description": "仿 Linux shell 文件处理命令的百度网盘命令行客户端.",
    "architecture": {
        "64bit": {
            "url": "https://github.com/qjfoidnh/BaiduPCS-Go/releases/download/v4.0.1/BaiduPCS-Go-v4.0.1-windows-x64.zip",
            "hash": "bb3bc2409e55820d681daef880a6949748fbc81d740952c2b2c05c28a075a4ee",
            "bin": [
                [
                    "BaiduPCS-Go-v4.0.1-windows-x64\\BaiduPCS-Go.exe",
                    "baidupcs"
                ]
            ]
        },
        "arm64": {
            "url": "https://github.com/qjfoidnh/BaiduPCS-Go/releases/download/v4.0.1/BaiduPCS-Go-v4.0.1-windows-arm.zip",
            "hash": "1ca4e68a791ac8efe185ba629cae687482a05bae4b7319d21098cecea7528be0",
            "bin": [
                [
                    "BaiduPCS-Go-v4.0.1-windows-arm\\BaiduPCS-Go.exe",
                    "baidupcs"
                ]
            ]
        },
        "32bit": {
            "url": "https://github.com/qjfoidnh/BaiduPCS-Go/releases/download/v4.0.1/BaiduPCS-Go-v4.0.1-windows-x86.zip",
            "hash": "17f9a27d4a6144a062e4771dfa7c7efd206fa9b97cc91a465cc26f9e9a02db9f",
            "bin": [
                [
                    "BaiduPCS-Go-v4.0.1-windows-x86\\BaiduPCS-Go.exe",
                    "baidupcs"
                ]
            ]
        }
    },
    "checkver": "github",
    "autoupdate": {
        "architecture": {
            "64bit": {
                "url": "https://github.com/qjfoidnh/BaiduPCS-Go/releases/download/v$version/BaiduPCS-Go-v$version-windows-x64.zip",
                "bin": [
                    [
                        "BaiduPCS-Go-v$version-windows-x64\\BaiduPCS-Go.exe",
                        "baidupcs"
                    ]
                ]
            },
            "arm64": {
                "url": "https://github.com/qjfoidnh/BaiduPCS-Go/releases/download/v$version/BaiduPCS-Go-v$version-windows-arm.zip",
                "bin": [
                    [
                        "BaiduPCS-Go-v$version-windows-arm\\BaiduPCS-Go.exe",
                        "baidupcs"
                    ]
                ]
            },
            "32bit": {
                "url": "https://github.com/qjfoidnh/BaiduPCS-Go/releases/download/v$version/BaiduPCS-Go-v$version-windows-x86.zip",
                "bin": [
                    [
                        "BaiduPCS-Go-v$version-windows-x86\\BaiduPCS-Go.exe",
                        "baidupcs"
                    ]
                ]
            }
        }
    }
}
